{
  "version": "0.1.0",
  "name": "anchor_mint_sell_nft",
  "instructions": [
    {
      "name": "mint",
      "accounts": [
        {
          "name": "metadata",
          "isMut": true,
          "isSigner": false
        },
        {
          "name": "masterEdition",
          "isMut": true,
          "isSigner": false
        },
        {
          "name": "mint",
          "isMut": true,
          "isSigner": true
        },
        {
          "name": "tokenAccount",
          "isMut": true,
          "isSigner": false
        },
        {
          "name": "mintAuthority",
          "isMut": true,
          "isSigner": true
        },
        {
          "name": "rent",
          "isMut": false,
          "isSigner": false
        },
        {
          "name": "systemProgram",
          "isMut": false,
          "isSigner": false
        },
        {
          "name": "tokenProgram",
          "isMut": false,
          "isSigner": false
        },
        {
          "name": "associatedTokenProgram",
          "isMut": false,
          "isSigner": false
        },
        {
          "name": "tokenMetadataProgram",
          "isMut": false,
          "isSigner": false
        }
      ],
      "args": [
        {
          "name": "metadataTitle",
          "type": "string"
        },
        {
          "name": "metadataSymbol",
          "type": "string"
        },
        {
          "name": "metadataUri",
          "type": "string"
        },
        {
          "name": "supply",
          "type": "u64"
        }
      ]
    },
    {
      "name": "minttoken",
      "accounts": [
        {
          "name": "mint",
          "isMut": true,
          "isSigner": true
        },
        {
          "name": "tokenAccount",
          "isMut": true,
          "isSigner": false
        },
        {
          "name": "mintAuthority",
          "isMut": true,
          "isSigner": true
        },
        {
          "name": "rent",
          "isMut": false,
          "isSigner": false
        },
        {
          "name": "systemProgram",
          "isMut": false,
          "isSigner": false
        },
        {
          "name": "tokenProgram",
          "isMut": false,
          "isSigner": false
        },
        {
          "name": "associatedTokenProgram",
          "isMut": false,
          "isSigner": false
        }
      ],
      "args": [
        {
          "name": "supply",
          "type": "u64"
        }
      ]
    },
    {
      "name": "sell",
      "accounts": [
        {
          "name": "mint",
          "isMut": true,
          "isSigner": false
        },
        {
          "name": "splmint",
          "isMut": true,
          "isSigner": false
        },
        {
          "name": "ownerTokenAccount",
          "isMut": true,
          "isSigner": false
        },
        {
          "name": "ownerSplTokenAccount",
          "isMut": true,
          "isSigner": false
        },
        {
          "name": "ownerAuthority",
          "isMut": true,
          "isSigner": true
        },
        {
          "name": "treasuryWallet",
          "isMut": true,
          "isSigner": true
        },
        {
          "name": "buyerTokenAccount",
          "isMut": true,
          "isSigner": false
        },
        {
          "name": "buyerSplTokenAccount",
          "isMut": true,
          "isSigner": false
        },
        {
          "name": "buyerAuthority",
          "isMut": true,
          "isSigner": true
        },
        {
          "name": "rent",
          "isMut": false,
          "isSigner": false
        },
        {
          "name": "systemProgram",
          "isMut": false,
          "isSigner": false
        },
        {
          "name": "tokenProgram",
          "isMut": false,
          "isSigner": false
        },
        {
          "name": "associatedTokenProgram",
          "isMut": false,
          "isSigner": false
        }
      ],
      "args": [
        {
          "name": "saleLamports",
          "type": "u64"
        },
        {
          "name": "amountTransfer",
          "type": "u64"
        }
      ]
    }
  ],
  "metadata": {
    "address": "H4cywKiiWQK9ShnEzQ7e2L3yXMgms2tcmPmPXciZsP5v"
  }
}